auto_flutter/__init__.py
auto_flutter/__main__.py
auto_flutter-1.1.0.dist-info/LICENSE
auto_flutter-1.1.0.dist-info/METADATA
auto_flutter-1.1.0.dist-info/WHEEL
auto_flutter-1.1.0.dist-info/entry_points.txt
auto_flutter-1.1.0.dist-info/top_level.txt
auto_flutter-1.1.0.dist-info/RECORD
