Metadata-Version: 2.1
Name: auto-flutter
Version: 1.1.0
Summary: Auto Flutter is a python package to create structured base flutter projects.
Home-page: https://github.com/jspw/Auto-Flutter
Author: jspw
Author-email: mhshifat757@gmail.com
License: GNU General Public License v3.0
Platform: UNKNOWN
Classifier: Programming Language :: Python :: 3
Classifier: License :: OSI Approved :: GNU General Public License v3 (GPLv3)
Classifier: Operating System :: POSIX :: Linux
Requires-Python: >=3.6
